fortigate_vpn_login/__init__.py
fortigate_vpn_login/cli.py
fortigate_vpn_login/config.py
fortigate_vpn_login/fortigate.py
fortigate_vpn_login/utils.py
fortigate_vpn_login/webserver.py
fortigate_vpn_login-0.5.dist-info/LICENSE
fortigate_vpn_login-0.5.dist-info/METADATA
fortigate_vpn_login-0.5.dist-info/WHEEL
fortigate_vpn_login-0.5.dist-info/entry_points.txt
fortigate_vpn_login-0.5.dist-info/top_level.txt
fortigate_vpn_login-0.5.dist-info/RECORD
