Metadata-Version: 2.1
Name: fortigate-vpn-login
Version: 0.5
Summary: Uses openconnect to connect to Fortinet VPNs, with extra features
Home-page: https://github.com/eitchugo/fortigate-vpn-login
Author: Hugo Cisneiros
Author-email: hugo.cisneiros@gmail.com
Keywords: vpn,security,openconnect,fortinet
Classifier: Development Status :: 5 - Production/Stable
Classifier: Environment :: Console
Classifier: Intended Audience :: Developers
Classifier: Intended Audience :: System Administrators
Classifier: Intended Audience :: Information Technology
Classifier: License :: OSI Approved :: GNU General Public License v3 (GPLv3)
Classifier: Programming Language :: Python :: 3.8
Classifier: Programming Language :: Python :: 3.9
Classifier: Programming Language :: Python :: 3.10
Classifier: Programming Language :: Python :: 3.11
Classifier: Programming Language :: Python :: 3 :: Only
Classifier: Topic :: Security
Classifier: Topic :: System :: Networking
Requires-Python: >=3.8, <4
License-File: LICENSE
Requires-Dist: requests ==2.31.0
Requires-Dist: xmltodict ==0.13.0
Requires-Dist: beautifulsoup4 ==4.12.2
Requires-Dist: werkzeug ==2.3.6
Requires-Dist: markupsafe ==2.1.3
Requires-Dist: psutil ==5.9.5
Provides-Extra: dev
Requires-Dist: build ==0.10.0 ; extra == 'dev'
Requires-Dist: twine-4.0.2 ; extra == 'dev'
